{
    "tts_checkpoint":"/media/erogol/data_ssd/Models/libri_tts/5049/best_model.pth.tar",     // tts checkpoint file
    "tts_config":"/media/erogol/data_ssd/Models/libri_tts/5049/config.json",     // tts config.json file
    "tts_speakers": null,           // json file listing speaker ids. null if no speaker embedding.
    "wavernn_lib_path": null,   // Rootpath to wavernn project folder to be imported. If this is null, model uses GL for speech synthesis.
    "wavernn_file":null, // wavernn checkpoint file name
    "wavernn_config": null, // wavernn config file
    "is_wavernn_batched":true, 
    "pwgan_lib_path": null,   // Rootpath to pwgan project folder to be imported. If this is null, model uses GL for speech synthesis.
    "pwgan_type":null,  // pwgan type: "pw" or "mel"
    "pwgan_file":null, // pwgan checkpoint file name
    "pwgan_config": null, // pwgan config file
    "port": 5002,
    "use_cuda": true,
    "debug": true
}
